zwoeafpy
