Metadata-Version: 2.1
Name: zwoeafpy
Version: 0.3.0
Summary: Python binding for the ZWO Electronic Automatic Focuser (EAF) SDK
Home-page: https://github.com/Willcarr99/zwoeafpy
Author: William Fox
Author-email: foxwilliamcarr@gmail.com
Classifier: Programming Language :: Python :: 3
Classifier: License :: OSI Approved :: MIT License
Classifier: Operating System :: OS Independent
Requires-Python: >=3.2
